jackal/__init__.py
jackal/config.py
jackal/core.py
jackal/documents.py
jackal/utils.py
jackal/scripts/__init__.py
jackal/scripts/cme.py
jackal/scripts/credentials.py
jackal/scripts/domaindump.py
jackal/scripts/filter.py
jackal/scripts/head_scanner.py
jackal/scripts/hosts.py
jackal/scripts/modify.py
jackal/scripts/named_pipes.py
jackal/scripts/nessus.py
jackal/scripts/netdiscover.py
jackal/scripts/nmap.py
jackal/scripts/ranges.py
jackal/scripts/services.py
jackal/scripts/status.py
jackal/scripts/tags.py
jackal/scripts/tomcat_brute.py
jackal/scripts/user-bak.py
jackal/scripts/user.py
jackal-0.6.7.dist-info/DESCRIPTION.rst
jackal-0.6.7.dist-info/METADATA
jackal-0.6.7.dist-info/RECORD
jackal-0.6.7.dist-info/WHEEL
jackal-0.6.7.dist-info/entry_points.txt
jackal-0.6.7.dist-info/metadata.json
jackal-0.6.7.dist-info/top_level.txt
