Metadata-Version: 2.0
Name: jackal
Version: 0.6.7
Summary: Jackal provides a way to store results from hacking tools in a single place.
Home-page: https://github.com/mwgielen/jackal/
Author: Matthijs Gielen
Author-email: github@mwgielen.com
License: MIT
Platform: UNKNOWN
Classifier: Development Status :: 3 - Alpha
Classifier: License :: OSI Approved :: MIT License
Classifier: Programming Language :: Python :: 3 :: Only
Requires-Dist: dnspython
Requires-Dist: elasticsearch-dsl
Requires-Dist: gevent
Requires-Dist: grequests
Requires-Dist: python-libnmap
Requires-Dist: requests
